gps_uvsq_utils/__init__.py
gps_uvsq_utils/db_connection.py
gps_uvsq_utils/gps_helpers.py
gps_uvsq_utils/st_helpers.py
gps_uvsq_utils/assets/uvsq.png
gps_uvsq_utils-1.0.1.dist-info/METADATA
gps_uvsq_utils-1.0.1.dist-info/WHEEL
gps_uvsq_utils-1.0.1.dist-info/top_level.txt
gps_uvsq_utils-1.0.1.dist-info/RECORD
